msgspec/msgpack.pyi
msgspec/yaml.py
msgspec/structs.py
msgspec/py.typed
msgspec/inspect.py
msgspec/structs.pyi
msgspec/msgpack.py
msgspec/__init__.py
msgspec/json.pyi
msgspec/_version.py
msgspec/__init__.pyi
msgspec/_core.cpython-311-aarch64-linux-musl.so
msgspec/toml.py
msgspec/_json_schema.py
msgspec/json.py
msgspec/_utils.py
litestar_msgspec-0.19.0.dist-info/METADATA
litestar_msgspec-0.19.0.dist-info/RECORD
litestar_msgspec-0.19.0.dist-info/top_level.txt
litestar_msgspec-0.19.0.dist-info/WHEEL
litestar_msgspec-0.19.0.dist-info/LICENSE
